maghsoodtest/__init__.py
maghsoodtest/main.py
maghsoodtest-0.1.8.dist-info/WHEEL
maghsoodtest-0.1.8.dist-info/METADATA
maghsoodtest-0.1.8.dist-info/RECORD
