Metadata-Version: 2.1
Name: maghsoodtest
Version: 0.1.8
Summary: this is simple python package ...
Author-email: maghsood026 <maghsood95@gmail.com>
Requires-Python: >=3.7
